celeste.py
celeste-1.0a2.dist-info/LICENSE
celeste-1.0a2.dist-info/METADATA
celeste-1.0a2.dist-info/WHEEL
celeste-1.0a2.dist-info/top_level.txt
celeste-1.0a2.dist-info/RECORD
